MANIFEST.in
setup.cfg
setup.py
superspider/.gitattributes
superspider/.gitignore
superspider/__init__.py
superspider/__main__.py
superspider/scraper.py
superspider/template.html
superspider.egg-info/PKG-INFO
superspider.egg-info/SOURCES.txt
superspider.egg-info/dependency_links.txt
superspider.egg-info/top_level.txt
superspider/__pycache__/__init__.cpython-34.pyc
superspider/__pycache__/__main__.cpython-34.pyc
superspider/__pycache__/scraper.cpython-34.pyc