Metadata-Version: 1.1
Name: superspider
Version: 0.1.15
Summary: A web scraper that adapts to any web page structure, and design.
Home-page: https://github.com/CalderWhite/superspider
Author: Calder White
Author-email: calderwhite1@gmail.com
License: UNKNOWN
Download-URL: https://github.com/CalderWhite/superspider/archive/master.zip
Platform: UNKNOWN
